userpathsfinder/__init__.py
userpathsfinder/paths.py
userpathsfinder-1.0.0.dist-info/METADATA
userpathsfinder-1.0.0.dist-info/WHEEL
userpathsfinder-1.0.0.dist-info/top_level.txt
userpathsfinder-1.0.0.dist-info/RECORD
