Metadata-Version: 2.4
Name: userpathsfinder
Version: 1.0.0
Summary: A simple Python package to get common user folder paths
Classifier: Programming Language :: Python :: 3
Classifier: License :: OSI Approved :: MIT License
Classifier: Operating System :: OS Independent
Requires-Python: >=3.6
